pyasn1_alt_modules/__init__.py
pyasn1_alt_modules/opentypemap.py
pyasn1_alt_modules/pem.py
pyasn1_alt_modules/rfc1155.py
pyasn1_alt_modules/rfc1157.py
pyasn1_alt_modules/rfc1901.py
pyasn1_alt_modules/rfc1902.py
pyasn1_alt_modules/rfc1905.py
pyasn1_alt_modules/rfc2040.py
pyasn1_alt_modules/rfc2251.py
pyasn1_alt_modules/rfc2314.py
pyasn1_alt_modules/rfc2315.py
pyasn1_alt_modules/rfc2437.py
pyasn1_alt_modules/rfc2459.py
pyasn1_alt_modules/rfc2511.py
pyasn1_alt_modules/rfc2528.py
pyasn1_alt_modules/rfc2560.py
pyasn1_alt_modules/rfc2631.py
pyasn1_alt_modules/rfc2634.py
pyasn1_alt_modules/rfc2743.py
pyasn1_alt_modules/rfc2876.py
pyasn1_alt_modules/rfc2898.py
pyasn1_alt_modules/rfc2985.py
pyasn1_alt_modules/rfc2986.py
pyasn1_alt_modules/rfc3058.py
pyasn1_alt_modules/rfc3114.py
pyasn1_alt_modules/rfc3125.py
pyasn1_alt_modules/rfc3161.py
pyasn1_alt_modules/rfc3217.py
pyasn1_alt_modules/rfc3274.py
pyasn1_alt_modules/rfc3279.py
pyasn1_alt_modules/rfc3280.py
pyasn1_alt_modules/rfc3281.py
pyasn1_alt_modules/rfc3370.py
pyasn1_alt_modules/rfc3412.py
pyasn1_alt_modules/rfc3414.py
pyasn1_alt_modules/rfc3447.py
pyasn1_alt_modules/rfc3537.py
pyasn1_alt_modules/rfc3546.py
pyasn1_alt_modules/rfc3560.py
pyasn1_alt_modules/rfc3565.py
pyasn1_alt_modules/rfc3657.py
pyasn1_alt_modules/rfc3709.py
pyasn1_alt_modules/rfc3739.py
pyasn1_alt_modules/rfc3770.py
pyasn1_alt_modules/rfc3779.py
pyasn1_alt_modules/rfc3820.py
pyasn1_alt_modules/rfc3852.py
pyasn1_alt_modules/rfc3874.py
pyasn1_alt_modules/rfc4010.py
pyasn1_alt_modules/rfc4043.py
pyasn1_alt_modules/rfc4055.py
pyasn1_alt_modules/rfc4056.py
pyasn1_alt_modules/rfc4059.py
pyasn1_alt_modules/rfc4073.py
pyasn1_alt_modules/rfc4108.py
pyasn1_alt_modules/rfc4210.py
pyasn1_alt_modules/rfc4211.py
pyasn1_alt_modules/rfc4212.py
pyasn1_alt_modules/rfc4231.py
pyasn1_alt_modules/rfc4262.py
pyasn1_alt_modules/rfc4334.py
pyasn1_alt_modules/rfc4357.py
pyasn1_alt_modules/rfc4366.py
pyasn1_alt_modules/rfc4387.py
pyasn1_alt_modules/rfc4476.py
pyasn1_alt_modules-0.4.7.dist-info/licenses/LICENSE.txt
pyasn1_alt_modules-0.4.7.dist-info/METADATA
pyasn1_alt_modules-0.4.7.dist-info/WHEEL
pyasn1_alt_modules-0.4.7.dist-info/top_level.txt
pyasn1_alt_modules-0.4.7.dist-info/zip-safe
pyasn1_alt_modules-0.4.7.dist-info/RECORD
