Metadata-Version: 2.4
Name: pyasn1_alt_modules
Version: 0.4.7
Summary: An alternative collection of ASN.1-based protocol modules
Home-page: https://github.com/russhousley/pyasn1-alt-modules
Author: Russ Housley
Author-email: housley@vigilsec.com
Maintainer: Russ Housley
Maintainer-email: housley@vigilsec.com
License: BSD
Project-URL: Source, https://github.com/russhousley/pyasn1-alt-modules
Project-URL: Issues, https://github.com/russhousley/pyasn1-alt-modules/issues
Project-URL: Changelog, https://github.com/russhousley/pyasn1-alt-modules/blob/master/CHANGES.txt
Platform: any
Classifier: Development Status :: 5 - Production/Stable
Classifier: Environment :: Console
Classifier: Intended Audience :: Developers
Classifier: Intended Audience :: Education
Classifier: Intended Audience :: Information Technology
Classifier: Intended Audience :: System Administrators
Classifier: Intended Audience :: Telecommunications Industry
Classifier: Natural Language :: English
Classifier: Operating System :: OS Independent
Classifier: Programming Language :: Python :: 3
Classifier: Programming Language :: Python :: 3.10
Classifier: Programming Language :: Python :: 3.11
Classifier: Programming Language :: Python :: 3.12
Classifier: Programming Language :: Python :: 3.13
Classifier: Programming Language :: Python :: 3.14
Requires-Python: >=3.10
License-File: LICENSE.txt
Requires-Dist: pyasn1>=0.6.0
Dynamic: license-file
